cryoemservices/__init__.py
cryoemservices/cli/__init__.py
cryoemservices/cli/clem_align_and_merge.py
cryoemservices/cli/clem_process_raw_lifs.py
cryoemservices/cli/clem_process_raw_tiffs.py
cryoemservices/cli/dlq_rabbitmq.py
cryoemservices/cli/project_linker.py
cryoemservices/cli/resubmit_wrapper.py
cryoemservices/cli/run_wrapper.py
cryoemservices/cli/start_service.py
cryoemservices/pipeliner_plugins/__init__.py
cryoemservices/pipeliner_plugins/angular_distribution_plot.py
cryoemservices/pipeliner_plugins/angular_efficiency.py
cryoemservices/pipeliner_plugins/combine_star_files.py
cryoemservices/pipeliner_plugins/combine_star_job.py
cryoemservices/pipeliner_plugins/reextract.py
cryoemservices/pipeliner_plugins/symmetry_finder.py
cryoemservices/services/__init__.py
cryoemservices/services/bfactor_setup.py
cryoemservices/services/class2d.py
cryoemservices/services/class3d.py
cryoemservices/services/clem_align_and_merge.py
cryoemservices/services/clem_process_raw_lifs.py
cryoemservices/services/clem_process_raw_tiffs.py
cryoemservices/services/cluster_submission.py
cryoemservices/services/common_service.py
cryoemservices/services/cryolo.py
cryoemservices/services/ctffind.py
cryoemservices/services/denoise.py
cryoemservices/services/denoise_slurm.py
cryoemservices/services/extract.py
cryoemservices/services/extract_class.py
cryoemservices/services/icebreaker.py
cryoemservices/services/images.py
cryoemservices/services/images_plugins.py
cryoemservices/services/ispyb_connector.py
cryoemservices/services/membrain_seg.py
cryoemservices/services/motioncorr.py
cryoemservices/services/node_creator.py
cryoemservices/services/postprocess.py
cryoemservices/services/process_recipe.py
cryoemservices/services/refine3d.py
cryoemservices/services/select_classes.py
cryoemservices/services/select_particles.py
cryoemservices/services/tomo_align.py
cryoemservices/services/tomo_align_slurm.py
cryoemservices/services/topaz_pick.py
cryoemservices/util/__init__.py
cryoemservices-1.3.3.dist-info/licenses/LICENSE
cryoemservices-1.3.3.dist-info/METADATA
cryoemservices-1.3.3.dist-info/WHEEL
cryoemservices-1.3.3.dist-info/entry_points.txt
cryoemservices-1.3.3.dist-info/top_level.txt
cryoemservices-1.3.3.dist-info/RECORD
