Metadata-Version: 2.4
Name: cryoemservices
Version: 1.3.3
Summary: Services for CryoEM processing
Author-email: "Diamond Light Source - Data Analysis et al." <dataanalysis@diamond.ac.uk>
License: BSD 3-Clause License
Project-URL: Bug-Tracker, https://github.com/DiamondLightSource/cryoem-services/issues
Project-URL: GitHub, https://github.com/DiamondLightSource/cryoem-services
Keywords: cryoem-services
Classifier: Development Status :: 3 - Alpha
Classifier: Intended Audience :: Science/Research
Classifier: License :: OSI Approved :: BSD License
Classifier: Natural Language :: English
Classifier: Programming Language :: Python :: 3 :: Only
Classifier: Programming Language :: Python :: 3.10
Classifier: Programming Language :: Python :: 3.11
Classifier: Programming Language :: Python :: 3.12
Requires-Python: >=3.10
License-File: LICENSE
Requires-Dist: defusedxml
Requires-Dist: gemmi==0.6.5
Requires-Dist: graypy
Requires-Dist: healpy
Requires-Dist: icebreaker-em
Requires-Dist: ispyb>=11.1.1
Requires-Dist: mrcfile
Requires-Dist: numpy<2
Requires-Dist: pillow
Requires-Dist: plotly
Requires-Dist: pydantic>=2
Requires-Dist: pystackreg
Requires-Dist: readlif
Requires-Dist: requests
Requires-Dist: SimpleITK
Requires-Dist: starfile
Requires-Dist: stomp-py>8.1.1
Requires-Dist: tifffile
Requires-Dist: workflows>=3
Provides-Extra: dev
Requires-Dist: bump-my-version; extra == "dev"
Requires-Dist: ipykernel; extra == "dev"
Requires-Dist: pre-commit; extra == "dev"
Requires-Dist: pytest; extra == "dev"
Requires-Dist: pytest-datafiles; extra == "dev"
Requires-Dist: pytest-mock; extra == "dev"
Provides-Extra: torch
Requires-Dist: membrain-seg; extra == "torch"
Requires-Dist: topaz-em; extra == "torch"
Dynamic: license-file
